<?xml version="1.0" encoding="windows-1251" ?>
<string_table>
	<string id="pri_followers_start_dlg_21">
		<text>Выдвигаемся вдоль по улице. В случае чего - прикроешь.</text>
	</string>
	<string id="pri_followers_start_dlg_211">
		<text>Хорошо.</text>
	</string>
	<string id="pri_followers_start_dlg_31">
		<text>Спасибо за помощь, Меченый. Это был тяжёлый бой. Мы сделаем здесь привал. Если пойдёшь дальше, то расскажу тебе о местности. Если вернёшься назад по переходу и пойдёшь направо, то дойдёшь до автовокзала. Но там больно местность открытая и небезопасная. Если же пройти вперёд, то окажешься перед гостиницей. Справа от неё - база «Монолита». Те ребята без крыши. За базой - стадион. Мы планировали через него на станцию пробираться. Это всё.</text>
	</string>
	<string id="pri_followers_start_dlg_311">
		<text>Спасибо.</text>
	</string>
	<string id="pri_followers_start_dlg_41">
		<text>Спасибо за помощь. Удачи.</text>
	</string>
	<string id="pri_followers_start_dlg_411">
		<text>Пока.</text>
	</string>
	<string id="zdorovo_strelok">
		<text>Здорово, Стрелок!</text>
	</string>
	<string id="otkuda_znaesh">
		<text>Кто ты такой? И откуда ты про меня знаешь?</text>
	</string>
	<string id="my_zhe_sosedi">
		<text>Называй меня Тёмный дилер. Я здесь раньше в гостинице жил, рядом с твоим номером «26». А сейчас, как видишь, отдельную квартирку получил. С видом на город.</text>
	</string>
	<string id="strannyi_tip">
		<text>Странный ты тип. Даже про номер «26» в гостинице знаешь. Хотя... Может быть мы и встречались раньше, до того, как я попал в грузовик смерти.</text>
	</string>
	<string id="da_ne_boisya">
		<text>Ну, в общем-то... Будем считать, что встречались. Так или иначе, будь я тебе врагом, то давно бы пристрелил. Так что не паникуй. Я в Припяти решил торговлю наладить. Сталкерам теперь не помешает перевалочный пункт на Севере Зоны. Покупаю и продаю оружие, броню, боеприпасы и артефакты.</text>
	</string>
</string_table>
